asdftimer/__init__.py
asdftimer/asdf_timer.py
asdftimer-0.1.3.dist-info/LICENSE
asdftimer-0.1.3.dist-info/METADATA
asdftimer-0.1.3.dist-info/WHEEL
asdftimer-0.1.3.dist-info/RECORD
