Metadata-Version: 2.3
Name: asdftimer
Version: 0.1.3
Summary: Simple customizable Python timer.
License: MIT
Author: Nibs
Requires-Python: >=3.10
Classifier: License :: OSI Approved :: MIT License
Classifier: Programming Language :: Python :: 3
Classifier: Programming Language :: Python :: 3.10
Classifier: Programming Language :: Python :: 3.11
Classifier: Programming Language :: Python :: 3.12
Classifier: Programming Language :: Python :: 3.13
Project-URL: Homepage, https://github.com/snpm/asdftimer
